brad_enrichment/__init__.py
brad_enrichment/brad_enrichment.py
brad_enrichment/enrichment_cli.py
brad_enrichment/enrichment_endpoints.py
brad_enrichment/enrichment_literature_database.py
brad_enrichment-0.1.1.dist-info/METADATA
brad_enrichment-0.1.1.dist-info/WHEEL
brad_enrichment-0.1.1.dist-info/entry_points.txt
brad_enrichment-0.1.1.dist-info/top_level.txt
brad_enrichment-0.1.1.dist-info/RECORD
