Metadata-Version: 2.2
Name: brad-enrichment
Version: 0.1.1
Summary: A command-line tool for BRAD enrichment analysis
Home-page: https://github.com/JPickard1/BRAD-Enrichment
Author: Joshua Pickard
Author-email: jpic@umich.edu
Classifier: Programming Language :: Python :: 3
Classifier: License :: OSI Approved :: MIT License
Classifier: Operating System :: OS Independent
Requires-Python: >=3.10
Requires-Dist: openpyxl
Requires-Dist: click
Dynamic: author
Dynamic: author-email
Dynamic: classifier
Dynamic: description
Dynamic: description-content-type
Dynamic: home-page
Dynamic: requires-dist
Dynamic: requires-python
Dynamic: summary
